gnumpy.py
npmat.py
setup.py
gnumpy.egg-info/PKG-INFO
gnumpy.egg-info/SOURCES.txt
gnumpy.egg-info/dependency_links.txt
gnumpy.egg-info/top_level.txt