Metadata-Version: 1.0
Name: gnumpy
Version: 0.1
Summary: Gnumpy is a simple Python module that interfaces in a way almost identical to numpy, but does its computations on your computer's  GPU, using Cudamat.
Home-page: http://www.cs.toronto.edu/~tijmen/gnumpy.html
Author: Tijmen Tieleman
Author-email: UNKNOWN
License: BSD-derived (see LICENSE.txt)
Platform: UNKNOWN
